vector_db_sdk/__init__.py
vector_db_sdk/constants.py
vector_db_sdk/libvector.py
vector_db_sdk/pgvector.py
vector_db_sdk/tcvector.py
vector_db_sdk/util.py
vector_db_sdk/vector_db.py
vector_db_sdk-0.0.19.dist-info/licenses/LICENSE
vector_db_sdk-0.0.19.dist-info/METADATA
vector_db_sdk-0.0.19.dist-info/WHEEL
vector_db_sdk-0.0.19.dist-info/top_level.txt
vector_db_sdk-0.0.19.dist-info/RECORD
