Metadata-Version: 2.4
Name: vector-db-sdk
Version: 0.0.19
Summary: A unified Python SDK for vector databases supporting pgvector and tcvector
Home-page: https://github.com/your-username/vector-db-sdk
Author: v_fchtan
Author-email: v_fchtan <v_fchtan@global.tencent.com>
License: MIT
Project-URL: Homepage, https://github.com/your-username/vector-db-sdk
Project-URL: Repository, https://github.com/your-username/vector-db-sdk
Project-URL: Issues, https://github.com/your-username/vector-db-sdk/issues
Project-URL: Documentation, https://github.com/your-username/vector-db-sdk#readme
Keywords: vector database,pgvector,tcvector,embedding,similarity search
Classifier: Development Status :: 4 - Beta
Classifier: Intended Audience :: Developers
Classifier: License :: OSI Approved :: MIT License
Classifier: Programming Language :: Python :: 3
Classifier: Programming Language :: Python :: 3.8
Classifier: Programming Language :: Python :: 3.9
Classifier: Programming Language :: Python :: 3.10
Classifier: Programming Language :: Python :: 3.11
Classifier: Topic :: Database
Classifier: Topic :: Scientific/Engineering :: Artificial Intelligence
Requires-Python: >=3.8
License-File: LICENSE
Requires-Dist: psycopg2-binary>=2.9.0
Requires-Dist: loguru>=0.7.0
Requires-Dist: cachetools>=5.0.0
Requires-Dist: protobuf>=5.0.0
Requires-Dist: SQLAlchemy>=2.0.0
Requires-Dist: tcvectordb>=1.7.0
Requires-Dist: typing_extensions>=4.0.0
Provides-Extra: dev
Requires-Dist: pytest; extra == "dev"
Requires-Dist: pytest-cov; extra == "dev"
Requires-Dist: black; extra == "dev"
Requires-Dist: flake8; extra == "dev"
Requires-Dist: mypy; extra == "dev"
Provides-Extra: docs
Requires-Dist: sphinx; extra == "docs"
Requires-Dist: sphinx-rtd-theme; extra == "docs"
Dynamic: author
Dynamic: home-page
Dynamic: license-file
Dynamic: requires-python
